{
  "hash": "b50b251e",
  "configHash": "fb940e43",
  "lockfileHash": "7595ebe1",
  "browserHash": "a548b232",
  "optimized": {
    "react": {
      "src": "../../node_modules/react/index.js",
      "file": "react.js",
      "fileHash": "733cdd0e",
      "needsInterop": true
    },
    "react-dom/client": {
      "src": "../../node_modules/react-dom/client.js",
      "file": "react-dom_client.js",
      "fileHash": "f1a574cc",
      "needsInterop": true
    },
    "lucide-react": {
      "src": "../../node_modules/lucide-react/dist/esm/lucide-react.js",
      "file": "lucide-react.js",
      "fileHash": "3e072e2d",
      "needsInterop": false
    },
    "emailjs-com": {
      "src": "../../../node_modules/emailjs-com/es/index.js",
      "file": "emailjs-com.js",
      "fileHash": "e5f5af4c",
      "needsInterop": false
    }
  },
  "chunks": {
    "chunk-32E4H3EV": {
      "file": "chunk-32E4H3EV.js"
    },
    "chunk-G3PMV62Z": {
      "file": "chunk-G3PMV62Z.js"
    }
  }
}